pyoidn/__init__.py
pyoidn/capi.py
pyoidn/device.py
pyoidn/filter.py
pyoidn/utils.py
pyoidn/version.py
pyoidn/oidn/bin/oidnBenchmark
pyoidn/oidn/bin/oidnDenoise
pyoidn/oidn/bin/oidnTest
pyoidn/oidn/lib/libOpenImageDenoise.2.3.2.dylib
pyoidn/oidn/lib/libOpenImageDenoise.2.dylib
pyoidn/oidn/lib/libOpenImageDenoise.dylib
pyoidn/oidn/lib/libOpenImageDenoise_core.2.3.2.dylib
pyoidn/oidn/lib/libOpenImageDenoise_device_cpu.2.3.2.dylib
pyoidn/oidn/lib/libtbb.12.12.dylib
pyoidn/oidn/lib/libtbb.12.dylib
pyoidn/oidn/lib/libtbb.dylib
pyoidn/oidn/lib/cmake/OpenImageDenoise-2.3.2/OpenImageDenoiseConfig.cmake
pyoidn/oidn/lib/cmake/OpenImageDenoise-2.3.2/OpenImageDenoiseConfigVersion.cmake
pyoidn/oidn/lib/cmake/OpenImageDenoise-2.3.2/OpenImageDenoiseTargets-release.cmake
pyoidn/oidn/lib/cmake/OpenImageDenoise-2.3.2/OpenImageDenoiseTargets.cmake
pyoidn-2.3.2.dist-info/LICENSE
pyoidn-2.3.2.dist-info/METADATA
pyoidn-2.3.2.dist-info/WHEEL
pyoidn-2.3.2.dist-info/top_level.txt
pyoidn-2.3.2.dist-info/RECORD
